pythondata_cpu_cva6/__init__.py
pythondata_cpu_cva6/system_verilog/.editorconfig
pythondata_cpu_cva6/system_verilog/.gitignore
pythondata_cpu_cva6/system_verilog/.gitlab-ci.yml
pythondata_cpu_cva6/system_verilog/.gitmodules
pythondata_cpu_cva6/system_verilog/Bender.yml
pythondata_cpu_cva6/system_verilog/CHANGELOG.md
pythondata_cpu_cva6/system_verilog/CODEOWNERS
pythondata_cpu_cva6/system_verilog/CONTRIBUTING.md
pythondata_cpu_cva6/system_verilog/Flist.ariane
pythondata_cpu_cva6/system_verilog/LICENSE
pythondata_cpu_cva6/system_verilog/LICENSE.Berkeley
pythondata_cpu_cva6/system_verilog/LICENSE.SiFive
pythondata_cpu_cva6/system_verilog/Makefile
pythondata_cpu_cva6/system_verilog/README.md
pythondata_cpu_cva6/system_verilog/ariane.core
pythondata_cpu_cva6/system_verilog/config_pkg_generator.py
pythondata_cpu_cva6/system_verilog/init_testharness.do
pythondata_cpu_cva6/system_verilog/src_files.yml
pythondata_cpu_cva6/system_verilog/.github/ISSUE_TEMPLATE/task.yaml
pythondata_cpu_cva6/system_verilog/.github/workflows/ci.yml
pythondata_cpu_cva6/system_verilog/.gitlab-ci/core-v-verif-cva6.yml
pythondata_cpu_cva6/system_verilog/.gitlab-ci/cva6.yml
pythondata_cpu_cva6/system_verilog/ci/build-riscv-gcc.sh
pythondata_cpu_cva6/system_verilog/ci/build-riscv-tests.sh
pythondata_cpu_cva6/system_verilog/ci/check-tests.sh
pythondata_cpu_cva6/system_verilog/ci/default.config
pythondata_cpu_cva6/system_verilog/ci/float.config
pythondata_cpu_cva6/system_verilog/ci/get-torture.sh
pythondata_cpu_cva6/system_verilog/ci/gitlab-ci-emul.sh
pythondata_cpu_cva6/system_verilog/ci/install-dtc.sh
pythondata_cpu_cva6/system_verilog/ci/install-fesvr.sh
pythondata_cpu_cva6/system_verilog/ci/install-riscvpk.sh
pythondata_cpu_cva6/system_verilog/ci/install-spike.sh
pythondata_cpu_cva6/system_verilog/ci/install-verilator.sh
pythondata_cpu_cva6/system_verilog/ci/make-tmp.sh
pythondata_cpu_cva6/system_verilog/ci/path-setup.sh
pythondata_cpu_cva6/system_verilog/ci/riscv-amo-tests.list
pythondata_cpu_cva6-4.2.0.post384.dist-info/LICENSE
pythondata_cpu_cva6-4.2.0.post384.dist-info/METADATA
pythondata_cpu_cva6-4.2.0.post384.dist-info/WHEEL
pythondata_cpu_cva6-4.2.0.post384.dist-info/top_level.txt
pythondata_cpu_cva6-4.2.0.post384.dist-info/RECORD
