Metadata-Version: 2.1
Name: pythondata-cpu-cva6
Version: 4.2.0.post384
Summary: Python module containing system_verilog files for CVA6 cpu.
Home-page: https://github.com/litex-hub/pythondata-cpu-cva6
Author: LiteX Authors
Author-email: litex@googlegroups.com
License: UNKNOWN
Project-URL: Bug Tracker, https://github.com/litex-hub/pythondata-cpu-cva6/issues
Project-URL: Source Code, https://github.com/litex-hub/pythondata-cpu-cva6
Platform: UNKNOWN
Classifier: Programming Language :: Python :: 3
Classifier: License :: OSI Approved :: Apache Software License
Classifier: Operating System :: OS Independent
Requires-Python: >=3.5
License-File: LICENSE
